_incydr_cli/__init__.py
_incydr_cli/core.py
_incydr_cli/cursor.py
_incydr_cli/exceptions.py
_incydr_cli/file_readers.py
_incydr_cli/main.py
_incydr_cli/render.py
_incydr_cli/rich_utils.py
_incydr_cli/utils.py
_incydr_cli/cmds/actors.py
_incydr_cli/cmds/agents.py
_incydr_cli/cmds/alert_rules.py
_incydr_cli/cmds/alerts.py
_incydr_cli/cmds/audit_log.py
_incydr_cli/cmds/cases.py
_incydr_cli/cmds/departments.py
_incydr_cli/cmds/devices.py
_incydr_cli/cmds/directory_groups.py
_incydr_cli/cmds/file_events.py
_incydr_cli/cmds/files.py
_incydr_cli/cmds/legal_hold.py
_incydr_cli/cmds/models.py
_incydr_cli/cmds/orgs.py
_incydr_cli/cmds/risk_profiles.py
_incydr_cli/cmds/sessions.py
_incydr_cli/cmds/trusted_activities.py
_incydr_cli/cmds/users.py
_incydr_cli/cmds/utils.py
_incydr_cli/cmds/watchlists.py
_incydr_cli/cmds/options/alert_filter_options.py
_incydr_cli/cmds/options/audit_log_filter_options.py
_incydr_cli/cmds/options/event_filter_options.py
_incydr_cli/cmds/options/output_options.py
_incydr_cli/cmds/options/profile_filter_options.py
_incydr_cli/cmds/options/utils.py
_incydr_cli/logger/__init__.py
_incydr_cli/logger/enums.py
_incydr_cli/logger/handlers.py
_incydr_sdk/__init__.py
_incydr_sdk/__version__.py
_incydr_sdk/exceptions.py
_incydr_sdk/utils.py
_incydr_sdk/actors/client.py
_incydr_sdk/actors/models.py
_incydr_sdk/agents/client.py
_incydr_sdk/agents/models.py
_incydr_sdk/alert_rules/client.py
_incydr_sdk/alert_rules/models/request.py
_incydr_sdk/alert_rules/models/response.py
_incydr_sdk/alerts/client.py
_incydr_sdk/alerts/models/__init__.py
_incydr_sdk/alerts/models/alert.py
_incydr_sdk/alerts/models/enums.py
_incydr_sdk/alerts/models/request.py
_incydr_sdk/alerts/models/response.py
_incydr_sdk/audit_log/client.py
_incydr_sdk/audit_log/models.py
_incydr_sdk/cases/client.py
_incydr_sdk/cases/models.py
_incydr_sdk/core/auth.py
_incydr_sdk/core/client.py
_incydr_sdk/core/models.py
_incydr_sdk/core/settings.py
_incydr_sdk/core/utils.py
_incydr_sdk/customer/client.py
incydr-2.7.0.dist-info/METADATA
incydr-2.7.0.dist-info/WHEEL
incydr-2.7.0.dist-info/entry_points.txt
incydr-2.7.0.dist-info/licenses/LICENSE.txt
incydr-2.7.0.dist-info/RECORD
