Metadata-Version: 2.4
Name: incydr
Version: 2.7.0
Summary: Code42's Incydr Python SDK
Project-URL: Documentation, https://github.com/code42/incydr_python#readme
Project-URL: Issues, https://github.com/code42/incydr_python/issues
Project-URL: Source, https://github.com/code42/incydr_python/incydr
Author-email: Code42 <integrations@code42.com>
License-Expression: MIT
License-File: LICENSE.txt
Classifier: Development Status :: 4 - Beta
Classifier: Programming Language :: Python
Classifier: Programming Language :: Python :: 3.9
Classifier: Programming Language :: Python :: 3.10
Classifier: Programming Language :: Python :: 3.11
Classifier: Programming Language :: Python :: 3.12
Classifier: Programming Language :: Python :: 3.13
Classifier: Programming Language :: Python :: Implementation :: CPython
Classifier: Programming Language :: Python :: Implementation :: PyPy
Requires-Python: >=3.9
Requires-Dist: boltons
Requires-Dist: isodate
Requires-Dist: pydantic-settings
Requires-Dist: pydantic<2.12,>=2.11
Requires-Dist: python-dateutil
Requires-Dist: requests
Requires-Dist: requests-toolbelt
Requires-Dist: rich
Provides-Extra: cli
Requires-Dist: chardet; extra == 'cli'
Requires-Dist: click==8.1.*; extra == 'cli'
